{
  "name": "WhatsApp Outbound - School System",
  "nodes": [
    {
      "parameters": {
        "httpMethod": "POST",
        "path": "whatsapp-outbound",
        "responseMode": "responseNode",
        "options": {}
      },
      "id": "webhook-outbound",
      "name": "Webhook - Receive from Supabase",
      "type": "n8n-nodes-base.webhook",
      "typeVersion": 1,
      "position": [240, 300],
      "webhookId": "outbound-webhook-id"
    },
    {
      "parameters": {
        "conditions": {
          "options": {
            "caseSensitive": true,
            "leftValue": "",
            "typeValidation": "strict"
          },
          "conditions": [
            {
              "leftValue": "={{ $json.to }}",
              "rightValue": "",
              "operator": {
                "type": "string",
                "operation": "exists",
                "rightType": "simple"
              }
            },
            {
              "leftValue": "={{ $json.message }}",
              "rightValue": "",
              "operator": {
                "type": "string",
                "operation": "exists"
              }
            }
          ],
          "combinator": "and"
        },
        "options": {}
      },
      "id": "validate-data",
      "name": "Validate Required Fields",
      "type": "n8n-nodes-base.if",
      "typeVersion": 2,
      "position": [460, 300]
    },
    {
      "parameters": {
        "phoneNumberId": "YOUR_PHONE_NUMBER_ID",
        "to": "={{ $json.to }}",
        "messageType": "text",
        "message": "={{ $json.message }}",
        "additionalFields": {}
      },
      "id": "send-whatsapp",
      "name": "Send WhatsApp Message",
      "type": "n8n-nodes-base.whatsApp",
      "typeVersion": 1,
      "position": [680, 220],
      "credentials": {
        "whatsAppApi": {
          "id": "whatsapp-credentials-id",
          "name": "WhatsApp Business API"
        }
      }
    },
    {
      "parameters": {
        "respondWith": "json",
        "responseBody": "={{ { \"success\": true, \"messageId\": $json.id, \"status\": \"sent\" } }}"
      },
      "id": "success-response",
      "name": "Success Response",
      "type": "n8n-nodes-base.respondToWebhook",
      "typeVersion": 1,
      "position": [900, 220]
    },
    {
      "parameters": {
        "respondWith": "json",
        "responseBody": "={{ { \"success\": false, \"error\": \"Missing required fields: to, message\" } }}",
        "options": {
          "responseCode": 400
        }
      },
      "id": "error-response",
      "name": "Error Response - Missing Fields",
      "type": "n8n-nodes-base.respondToWebhook",
      "typeVersion": 1,
      "position": [680, 380]
    },
    {
      "parameters": {
        "respondWith": "json",
        "responseBody": "={{ { \"success\": false, \"error\": $json.error || \"Failed to send message\" } }}",
        "options": {
          "responseCode": 500
        }
      },
      "id": "whatsapp-error-response",
      "name": "Error Response - WhatsApp Failed",
      "type": "n8n-nodes-base.respondToWebhook",
      "typeVersion": 1,
      "position": [900, 380]
    }
  ],
  "connections": {
    "Webhook - Receive from Supabase": {
      "main": [
        [
          {
            "node": "Validate Required Fields",
            "type": "main",
            "index": 0
          }
        ]
      ]
    },
    "Validate Required Fields": {
      "main": [
        [
          {
            "node": "Send WhatsApp Message",
            "type": "main",
            "index": 0
          }
        ],
        [
          {
            "node": "Error Response - Missing Fields",
            "type": "main",
            "index": 0
          }
        ]
      ]
    },
    "Send WhatsApp Message": {
      "main": [
        [
          {
            "node": "Success Response",
            "type": "main",
            "index": 0
          }
        ]
      ]
    }
  },
  "pinData": {},
  "settings": {
    "executionOrder": "v1"
  },
  "staticData": null,
  "tags": [],
  "triggerCount": 0,
  "updatedAt": "2025-01-31T00:00:00.000Z",
  "versionId": "1"
}